raksha_ai/__init__.py
raksha_ai/scanner.py
raksha_ai/agents/__init__.py
raksha_ai/agents/goal_hijacking.py
raksha_ai/agents/recursive_loop.py
raksha_ai/agents/tool_misuse.py
raksha_ai/core/__init__.py
raksha_ai/core/detector.py
raksha_ai/core/guard.py
raksha_ai/core/models.py
raksha_ai/detectors/__init__.py
raksha_ai/detectors/data_exfiltration.py
raksha_ai/detectors/pii.py
raksha_ai/detectors/prompt_injection.py
raksha_ai/detectors/toxicity.py
raksha_ai/integrations/__init__.py
raksha_ai/integrations/phoenix/__init__.py
raksha_ai/integrations/phoenix/evaluator.py
raksha_ai/integrations/phoenix/tracer.py
raksha_ai/rules/__init__.py
raksha_ai/rules/rule_engine.py
raksha_ai/utils/__init__.py
raksha_ai/utils/config.py
raksha_ai-0.1.1.dist-info/licenses/LICENSE
raksha_ai-0.1.1.dist-info/METADATA
raksha_ai-0.1.1.dist-info/WHEEL
raksha_ai-0.1.1.dist-info/top_level.txt
raksha_ai-0.1.1.dist-info/RECORD
