Metadata-Version: 2.4
Name: raksha-ai
Version: 0.1.1
Summary: Framework-agnostic AI security SDK with comprehensive threat detection for LLMs and AI agents
Author-email: Raksha AI Security <security@raksha.ai>
License: MIT
Project-URL: Homepage, https://github.com/cjtejasai/Raksha-AI
Project-URL: Repository, https://github.com/cjtejasai/Raksha-AI
Project-URL: Issues, https://github.com/cjtejasai/Raksha-AI/issues
Project-URL: Changelog, https://github.com/cjtejasai/Raksha-AI/releases
Keywords: ai-security,llm-security,prompt-injection,agent-security,owasp,phoenix,langchain,security-scanner,threat-detection
Classifier: Development Status :: 3 - Alpha
Classifier: Intended Audience :: Developers
Classifier: Topic :: Security
Classifier: Topic :: Scientific/Engineering :: Artificial Intelligence
Classifier: License :: OSI Approved :: MIT License
Classifier: Programming Language :: Python :: 3.9
Classifier: Programming Language :: Python :: 3.10
Classifier: Programming Language :: Python :: 3.11
Classifier: Programming Language :: Python :: 3.12
Classifier: Programming Language :: Python :: 3.13
Requires-Python: >=3.9
License-File: LICENSE
Requires-Dist: pydantic>=2.0.0
Requires-Dist: regex>=2023.0.0
Provides-Extra: phoenix
Requires-Dist: arize-phoenix>=4.0.0; extra == "phoenix"
Requires-Dist: opentelemetry-api>=1.20.0; extra == "phoenix"
Requires-Dist: opentelemetry-sdk>=1.20.0; extra == "phoenix"
Requires-Dist: opentelemetry-exporter-otlp-proto-http>=1.20.0; extra == "phoenix"
Provides-Extra: langchain
Requires-Dist: langchain>=0.1.0; extra == "langchain"
Provides-Extra: llamaindex
Requires-Dist: llama-index>=0.9.0; extra == "llamaindex"
Provides-Extra: llm
Requires-Dist: transformers>=4.30.0; extra == "llm"
Requires-Dist: torch>=2.0.0; extra == "llm"
Requires-Dist: tiktoken>=0.5.0; extra == "llm"
Provides-Extra: agents
Requires-Dist: tiktoken>=0.5.0; extra == "agents"
Provides-Extra: compliance
Requires-Dist: pyyaml>=6.0.0; extra == "compliance"
Provides-Extra: dev
Requires-Dist: pytest>=7.0.0; extra == "dev"
Requires-Dist: pytest-asyncio>=0.21.0; extra == "dev"
Requires-Dist: black>=23.0.0; extra == "dev"
Requires-Dist: ruff>=0.1.0; extra == "dev"
Requires-Dist: mypy>=1.0.0; extra == "dev"
Provides-Extra: all
Requires-Dist: raksha-ai[phoenix]; extra == "all"
Requires-Dist: raksha-ai[langchain]; extra == "all"
Requires-Dist: raksha-ai[llamaindex]; extra == "all"
Requires-Dist: raksha-ai[llm]; extra == "all"
Requires-Dist: raksha-ai[agents]; extra == "all"
Requires-Dist: raksha-ai[compliance]; extra == "all"
Dynamic: license-file
